jinja2_python_version/__init__.py
jinja2_python_version/python_version.py
jinja2_python_version-1.2.0.dist-info/LICENSE
jinja2_python_version-1.2.0.dist-info/WHEEL
jinja2_python_version-1.2.0.dist-info/METADATA
jinja2_python_version-1.2.0.dist-info/RECORD
